bus_user/__init__.py
bus_user/history.py
bus_user/i2c_client.py
bus_user/line_parser.py
bus_user/serial_client.py
bus_user/serial_derivatives.py
bus_user/serial_server.py
bus_user-0.4.16.dist-info/LICENSE
bus_user-0.4.16.dist-info/METADATA
bus_user-0.4.16.dist-info/WHEEL
bus_user-0.4.16.dist-info/top_level.txt
bus_user-0.4.16.dist-info/RECORD
