Metadata-Version: 2.1
Name: bus_user
Version: 0.4.16
Summary: work with equipment over buses like Serial/i2c/... as client and server
Home-page: https://github.com/centroid457/
Author: Andrei Starichenko
Author-email: centroid@mail.ru
Project-URL: Source, https://github.com/centroid457/bus_user
Keywords: serial,serial bus,pyserial,serial port,com port,comport,rs232,UART,TTL,serial client,serial server,serial emulator,i2c
Classifier: Topic :: Software Development :: Libraries :: Python Modules
Classifier: License :: OSI Approved :: MIT License
Classifier: Programming Language :: Python
Classifier: Programming Language :: Python :: 3 :: Only
Classifier: Programming Language :: Python :: 3.11
Classifier: Operating System :: OS Independent
Classifier: Intended Audience :: Developers
Classifier: Natural Language :: English
Classifier: Typing :: Typed
Requires-Python: >=3.6
License-File: LICENSE
